LICENSE.txt
setup.py
antidevinfo.egg-info/PKG-INFO
antidevinfo.egg-info/SOURCES.txt
antidevinfo.egg-info/dependency_links.txt
antidevinfo.egg-info/top_level.txt
code/__init__.py