Metadata-Version: 2.1
Name: antidevinfo
Version: 1.0
Summary: Library just for fun
Author: Anti-Dev-Info
Classifier: Programming Language :: Python :: 3
Classifier: Operating System :: OS Independent
Classifier: License :: OSI Approved :: MIT License
License-File: LICENSE.txt
